s3/__init__.py
s3/base.py
s3/bucket.py
s3/object.py
s3_api-0.2.4.dist-info/METADATA
s3_api-0.2.4.dist-info/WHEEL
s3_api-0.2.4.dist-info/top_level.txt
s3_api-0.2.4.dist-info/RECORD
